pull_md/__init__.py
pull_md-2025.1225.1016.dist-info/licenses/LICENSE
tests/__init__.py
tests/test.py
tests/test_pull_md.py
pull_md-2025.1225.1016.dist-info/METADATA
pull_md-2025.1225.1016.dist-info/WHEEL
pull_md-2025.1225.1016.dist-info/top_level.txt
pull_md-2025.1225.1016.dist-info/RECORD
