Metadata-Version: 2.4
Name: pull_md
Version: 2025.1225.1016
Summary: A simple Python package to convert URLs to Markdown.
Home-page: https://github.com/chigwell/pull_md
Author: Eugene Evstafev
Author-email: chigwel@gmail.com
License: MIT
Classifier: Programming Language :: Python :: 3
Classifier: License :: OSI Approved :: MIT License
Classifier: Operating System :: OS Independent
Requires-Python: >=3.6
License-File: LICENSE
Requires-Dist: requests>=2.25.1
Dynamic: author
Dynamic: author-email
Dynamic: classifier
Dynamic: description
Dynamic: description-content-type
Dynamic: home-page
Dynamic: license
Dynamic: license-file
Dynamic: requires-dist
Dynamic: requires-python
Dynamic: summary
